map_binning/__init__.py
map_binning/binning.py
map_binning/index_store.py
map_binning-0.3.3.dist-info/licenses/LICENSE
map_binning-0.3.3.dist-info/METADATA
map_binning-0.3.3.dist-info/WHEEL
map_binning-0.3.3.dist-info/top_level.txt
map_binning-0.3.3.dist-info/RECORD
